redpatch/__init__.py
redpatch/filebrowser.py
redpatch/filtersettings.py
redpatch/imagearea.py
redpatch/lesioncentre.py
redpatch/redpatch.py
redpatch/report.py
redpatch/subimage.py
redpatch-0.2.4.data/scripts/redpatch-batch-process
redpatch-0.2.4.data/scripts/redpatch-start
redpatch_notebooks/Find Scale Card Filter Settings.ipynb
redpatch_notebooks/Redpatch Basic Use Example.ipynb
redpatch_notebooks/Using Threshold Sliders.ipynb
redpatch_notebooks/__init__.py
redpatch_notebooks/leaf_and_square.jpg
redpatch_notebooks/single_input.jpg
redpatch-0.2.4.dist-info/LICENSE.txt
redpatch-0.2.4.dist-info/METADATA
redpatch-0.2.4.dist-info/WHEEL
redpatch-0.2.4.dist-info/top_level.txt
redpatch-0.2.4.dist-info/RECORD
